poetrytest_yxd_1020_2/__init__.py
poetrytest_yxd_1020_2/abc.py
poetrytest_yxd_1020_2-0.1.0.dist-info/WHEEL
poetrytest_yxd_1020_2-0.1.0.dist-info/METADATA
poetrytest_yxd_1020_2-0.1.0.dist-info/RECORD
