Metadata-Version: 2.1
Name: poetrytest-yxd-1020-2
Version: 0.1.0
Summary: 
Author: Xiaodong Yang
Author-email: xiaoyan@microsoft.com
Requires-Python: >=3.8,<4.0
Classifier: Programming Language :: Python :: 3
Classifier: Programming Language :: Python :: 3.8
Classifier: Programming Language :: Python :: 3.9
Classifier: Programming Language :: Python :: 3.10
Classifier: Programming Language :: Python :: 3.11
Requires-Dist: pydantic (>=1.10.2,<2.0.0)
